PytorchRengongzhinengYantaohuiChuyi/README.md
PytorchRengongzhinengYantaohuiChuyi/__init__.py
PytorchRengongzhinengYantaohuiChuyi/__main__.py
PytorchRengongzhinengYantaohuiChuyi/file.epub
PytorchRengongzhinengYantaohuiChuyi/index.html
PytorchRengongzhinengYantaohuiChuyi/css/__init__.py
PytorchRengongzhinengYantaohuiChuyi/css/annotations.css
PytorchRengongzhinengYantaohuiChuyi/css/main.css
PytorchRengongzhinengYantaohuiChuyi/css/normalize.css
PytorchRengongzhinengYantaohuiChuyi/css/popup.css
PytorchRengongzhinengYantaohuiChuyi/font/__init__.py
PytorchRengongzhinengYantaohuiChuyi/font/fontello.eot
PytorchRengongzhinengYantaohuiChuyi/font/fontello.svg
PytorchRengongzhinengYantaohuiChuyi/font/fontello.ttf
PytorchRengongzhinengYantaohuiChuyi/font/fontello.woff
PytorchRengongzhinengYantaohuiChuyi/img/__init__.py
PytorchRengongzhinengYantaohuiChuyi/img/annotator-glyph-sprite.png
PytorchRengongzhinengYantaohuiChuyi/img/annotator-icon-sprite.png
PytorchRengongzhinengYantaohuiChuyi/img/apple-touch-icon.png
PytorchRengongzhinengYantaohuiChuyi/img/cancelfullscreen.png
PytorchRengongzhinengYantaohuiChuyi/img/close.png
PytorchRengongzhinengYantaohuiChuyi/img/fullscreen.png
PytorchRengongzhinengYantaohuiChuyi/img/loader.gif
PytorchRengongzhinengYantaohuiChuyi/img/menu-icon.png
PytorchRengongzhinengYantaohuiChuyi/img/save.png
PytorchRengongzhinengYantaohuiChuyi/img/saved.png
PytorchRengongzhinengYantaohuiChuyi/img/settings-s.png
PytorchRengongzhinengYantaohuiChuyi/img/settings.png
PytorchRengongzhinengYantaohuiChuyi/img/star.png
PytorchRengongzhinengYantaohuiChuyi/js/__init__.py
PytorchRengongzhinengYantaohuiChuyi/js/epub.js
PytorchRengongzhinengYantaohuiChuyi/js/epub.min.js
PytorchRengongzhinengYantaohuiChuyi/js/epub.min.map
PytorchRengongzhinengYantaohuiChuyi/js/hooks.min.js
PytorchRengongzhinengYantaohuiChuyi/js/hooks.min.map
PytorchRengongzhinengYantaohuiChuyi/js/reader.js
PytorchRengongzhinengYantaohuiChuyi/js/reader.js.map
PytorchRengongzhinengYantaohuiChuyi/js/reader.min.js
pytorch_rengongzhineng_yantaohui_chuyi-2024.3.6.0.dist-info/METADATA
pytorch_rengongzhineng_yantaohui_chuyi-2024.3.6.0.dist-info/WHEEL
pytorch_rengongzhineng_yantaohui_chuyi-2024.3.6.0.dist-info/entry_points.txt
pytorch_rengongzhineng_yantaohui_chuyi-2024.3.6.0.dist-info/top_level.txt
pytorch_rengongzhineng_yantaohui_chuyi-2024.3.6.0.dist-info/RECORD
